profileqc/__init__.py
profileqc/boolean_handler.py
profileqc/config.py
profileqc/qc.py
profileqc/utils.py
profileqc/etc/DEV_dependencies.yaml
profileqc/etc/parameter_dependencies.json
profileqc/etc/qc_routines/qc_decrease.yaml
profileqc/etc/qc_routines/qc_diff.yaml
profileqc/etc/qc_routines/qc_increase.yaml
profileqc/etc/qc_routines/qc_range.yaml
profileqc/etc/qc_routines/qc_spike.yaml
profileqc/routines/__init__.py
profileqc/routines/continuous.py
profileqc/routines/dependencies.py
profileqc/routines/diff.py
profileqc/routines/position.py
profileqc/routines/range.py
profileqc/routines/spike.py
profileqc/routines/time.py
profileqc-0.0.2.dist-info/LICENSE
profileqc-0.0.2.dist-info/METADATA
profileqc-0.0.2.dist-info/WHEEL
profileqc-0.0.2.dist-info/top_level.txt
profileqc-0.0.2.dist-info/RECORD
